tinydsl/LICENSE
tinydsl/__init__.py
tinydsl/agent_tools/__init__.py
tinydsl/agent_tools/tinydsl_tool.py
tinydsl/api/__init__.py
tinydsl/api/main.py
tinydsl/api/routes_gli.py
tinydsl/api/routes_lexi.py
tinydsl/data/gli_examples.json
tinydsl/data/gli_grammar.lark
tinydsl/data/lexi_grammar.lark
tinydsl/data/lexi_tasks.json
tinydsl/gli/__init__.py
tinydsl/gli/gli.py
tinydsl/gli/renderers.py
tinydsl/lexi/__init__.py
tinydsl/lexi/lexi.py
tinydsl/lexi/lexi_evaluator.py
tinydsl/lexi/lexi_memory.py
tinydsl/parser/__init__.py
tinydsl/parser/base_parser.py
tinydsl/parser/lark_gli_parser.py
tinydsl/parser/lark_lexi_parser.py
tinydsl/parser/lark_math_parser.py
tinydsl-0.0.6.dist-info/METADATA
tinydsl-0.0.6.dist-info/WHEEL
tinydsl-0.0.6.dist-info/top_level.txt
tinydsl-0.0.6.dist-info/RECORD
