Metadata-Version: 2.4
Name: tinydsl
Version: 0.0.6
Summary: A modular agent-ready framework for exploring domain-specific languages (DSLs)
Author: Deepak
Project-URL: Homepage, https://github.com/deepsaia/tinydsl
Project-URL: Repository, https://github.com/deepsaia/tinydsl
Project-URL: Documentation, https://github.com/deepsaia/tinydsl#readme
Project-URL: Issues, https://github.com/deepsaia/tinydsl/issues
Keywords: tinydsl,dsl,domain specific language,agent
Classifier: Programming Language :: Python :: 3
Classifier: Operating System :: OS Independent
Classifier: Development Status :: 4 - Beta
Classifier: Intended Audience :: Developers
Classifier: License :: OSI Approved :: Apache Software License
Requires-Python: >=3.12
Requires-Dist: fastapi>=0.119.0
Requires-Dist: lark>=1.3.0
Requires-Dist: pillow>=12.0.0
Requires-Dist: requests>=2.32.5
Requires-Dist: uvicorn>=0.38.0
